{
  "best_global_step": 7680,
  "best_metric": 1.5091774463653564,
  "best_model_checkpoint": "ch_lora_checkpoints/checkpoint-7680",
  "epoch": 2.0,
  "eval_steps": 500,
  "global_step": 7680,
  "is_hyper_param_search": false,
  "is_local_process_zero": true,
  "is_world_process_zero": true,
  "log_history": [
    {
      "epoch": 0.013020833333333334,
      "grad_norm": 0.061880193650722504,
      "learning_rate": 9.957465277777777e-05,
      "loss": 1.73,
      "step": 50
    },
    {
      "epoch": 0.026041666666666668,
      "grad_norm": 0.07816106826066971,
      "learning_rate": 9.914062500000001e-05,
      "loss": 1.7307,
      "step": 100
    },
    {
      "epoch": 0.0390625,
      "grad_norm": 0.08705095946788788,
      "learning_rate": 9.870659722222222e-05,
      "loss": 1.6537,
      "step": 150
    },
    {
      "epoch": 0.052083333333333336,
      "grad_norm": 0.2105398029088974,
      "learning_rate": 9.827256944444445e-05,
      "loss": 1.6708,
      "step": 200
    },
    {
      "epoch": 0.06510416666666667,
      "grad_norm": 0.10623376071453094,
      "learning_rate": 9.783854166666667e-05,
      "loss": 1.6253,
      "step": 250
    },
    {
      "epoch": 0.078125,
      "grad_norm": 0.09230164438486099,
      "learning_rate": 9.74045138888889e-05,
      "loss": 1.6214,
      "step": 300
    },
    {
      "epoch": 0.09114583333333333,
      "grad_norm": 0.14380799233913422,
      "learning_rate": 9.697048611111111e-05,
      "loss": 1.6362,
      "step": 350
    },
    {
      "epoch": 0.10416666666666667,
      "grad_norm": 0.17537429928779602,
      "learning_rate": 9.653645833333333e-05,
      "loss": 1.6597,
      "step": 400
    },
    {
      "epoch": 0.1171875,
      "grad_norm": 0.13106770813465118,
      "learning_rate": 9.610243055555556e-05,
      "loss": 1.6095,
      "step": 450
    },
    {
      "epoch": 0.13020833333333334,
      "grad_norm": 0.11380577087402344,
      "learning_rate": 9.566840277777777e-05,
      "loss": 1.6053,
      "step": 500
    },
    {
      "epoch": 0.14322916666666666,
      "grad_norm": 0.09938590973615646,
      "learning_rate": 9.523437500000001e-05,
      "loss": 1.6183,
      "step": 550
    },
    {
      "epoch": 0.15625,
      "grad_norm": 0.12118478864431381,
      "learning_rate": 9.480034722222223e-05,
      "loss": 1.6565,
      "step": 600
    },
    {
      "epoch": 0.16927083333333334,
      "grad_norm": 0.12895633280277252,
      "learning_rate": 9.436631944444445e-05,
      "loss": 1.6333,
      "step": 650
    },
    {
      "epoch": 0.18229166666666666,
      "grad_norm": 0.1229342594742775,
      "learning_rate": 9.393229166666667e-05,
      "loss": 1.6654,
      "step": 700
    },
    {
      "epoch": 0.1953125,
      "grad_norm": 0.1181139126420021,
      "learning_rate": 9.34982638888889e-05,
      "loss": 1.6367,
      "step": 750
    },
    {
      "epoch": 0.20833333333333334,
      "grad_norm": 0.12862595915794373,
      "learning_rate": 9.306423611111112e-05,
      "loss": 1.6559,
      "step": 800
    },
    {
      "epoch": 0.22135416666666666,
      "grad_norm": 0.15059177577495575,
      "learning_rate": 9.263020833333333e-05,
      "loss": 1.6411,
      "step": 850
    },
    {
      "epoch": 0.234375,
      "grad_norm": 0.20529434084892273,
      "learning_rate": 9.219618055555556e-05,
      "loss": 1.6808,
      "step": 900
    },
    {
      "epoch": 0.24739583333333334,
      "grad_norm": 0.1219281554222107,
      "learning_rate": 9.176215277777778e-05,
      "loss": 1.5861,
      "step": 950
    },
    {
      "epoch": 0.2604166666666667,
      "grad_norm": 0.1990395486354828,
      "learning_rate": 9.1328125e-05,
      "loss": 1.6371,
      "step": 1000
    },
    {
      "epoch": 0.2734375,
      "grad_norm": 0.15017254650592804,
      "learning_rate": 9.089409722222223e-05,
      "loss": 1.626,
      "step": 1050
    },
    {
      "epoch": 0.2864583333333333,
      "grad_norm": 0.1699303239583969,
      "learning_rate": 9.046006944444446e-05,
      "loss": 1.5955,
      "step": 1100
    },
    {
      "epoch": 0.2994791666666667,
      "grad_norm": 0.15927448868751526,
      "learning_rate": 9.002604166666667e-05,
      "loss": 1.6463,
      "step": 1150
    },
    {
      "epoch": 0.3125,
      "grad_norm": 0.3151824176311493,
      "learning_rate": 8.959201388888889e-05,
      "loss": 1.6145,
      "step": 1200
    },
    {
      "epoch": 0.3255208333333333,
      "grad_norm": 0.14904320240020752,
      "learning_rate": 8.915798611111112e-05,
      "loss": 1.6069,
      "step": 1250
    },
    {
      "epoch": 0.3385416666666667,
      "grad_norm": 0.17179837822914124,
      "learning_rate": 8.872395833333334e-05,
      "loss": 1.6388,
      "step": 1300
    },
    {
      "epoch": 0.3515625,
      "grad_norm": 0.1633238047361374,
      "learning_rate": 8.828993055555555e-05,
      "loss": 1.5932,
      "step": 1350
    },
    {
      "epoch": 0.3645833333333333,
      "grad_norm": 0.16047993302345276,
      "learning_rate": 8.785590277777778e-05,
      "loss": 1.5843,
      "step": 1400
    },
    {
      "epoch": 0.3776041666666667,
      "grad_norm": 0.14400649070739746,
      "learning_rate": 8.7421875e-05,
      "loss": 1.6383,
      "step": 1450
    },
    {
      "epoch": 0.390625,
      "grad_norm": 0.18192577362060547,
      "learning_rate": 8.698784722222223e-05,
      "loss": 1.6222,
      "step": 1500
    },
    {
      "epoch": 0.4036458333333333,
      "grad_norm": 0.15439417958259583,
      "learning_rate": 8.655381944444445e-05,
      "loss": 1.6576,
      "step": 1550
    },
    {
      "epoch": 0.4166666666666667,
      "grad_norm": 0.1645577996969223,
      "learning_rate": 8.611979166666668e-05,
      "loss": 1.6412,
      "step": 1600
    },
    {
      "epoch": 0.4296875,
      "grad_norm": 0.1866406798362732,
      "learning_rate": 8.568576388888889e-05,
      "loss": 1.639,
      "step": 1650
    },
    {
      "epoch": 0.4427083333333333,
      "grad_norm": 0.13491278886795044,
      "learning_rate": 8.525173611111111e-05,
      "loss": 1.6623,
      "step": 1700
    },
    {
      "epoch": 0.4557291666666667,
      "grad_norm": 0.14521466195583344,
      "learning_rate": 8.481770833333334e-05,
      "loss": 1.6199,
      "step": 1750
    },
    {
      "epoch": 0.46875,
      "grad_norm": 0.1650928407907486,
      "learning_rate": 8.438368055555555e-05,
      "loss": 1.5908,
      "step": 1800
    },
    {
      "epoch": 0.4817708333333333,
      "grad_norm": 0.16695041954517365,
      "learning_rate": 8.394965277777777e-05,
      "loss": 1.6364,
      "step": 1850
    },
    {
      "epoch": 0.4947916666666667,
      "grad_norm": 0.1692594438791275,
      "learning_rate": 8.351562500000001e-05,
      "loss": 1.6316,
      "step": 1900
    },
    {
      "epoch": 0.5078125,
      "grad_norm": 0.14149446785449982,
      "learning_rate": 8.308159722222222e-05,
      "loss": 1.6361,
      "step": 1950
    },
    {
      "epoch": 0.5208333333333334,
      "grad_norm": 0.15575428307056427,
      "learning_rate": 8.264756944444445e-05,
      "loss": 1.6462,
      "step": 2000
    },
    {
      "epoch": 0.5338541666666666,
      "grad_norm": 0.16006195545196533,
      "learning_rate": 8.221354166666667e-05,
      "loss": 1.5985,
      "step": 2050
    },
    {
      "epoch": 0.546875,
      "grad_norm": 0.2026202380657196,
      "learning_rate": 8.17795138888889e-05,
      "loss": 1.6752,
      "step": 2100
    },
    {
      "epoch": 0.5598958333333334,
      "grad_norm": 0.17437417805194855,
      "learning_rate": 8.134548611111111e-05,
      "loss": 1.5717,
      "step": 2150
    },
    {
      "epoch": 0.5729166666666666,
      "grad_norm": 0.21759867668151855,
      "learning_rate": 8.091145833333333e-05,
      "loss": 1.6088,
      "step": 2200
    },
    {
      "epoch": 0.5859375,
      "grad_norm": 0.19964662194252014,
      "learning_rate": 8.047743055555556e-05,
      "loss": 1.6458,
      "step": 2250
    },
    {
      "epoch": 0.5989583333333334,
      "grad_norm": 0.18959268927574158,
      "learning_rate": 8.004340277777777e-05,
      "loss": 1.6212,
      "step": 2300
    },
    {
      "epoch": 0.6119791666666666,
      "grad_norm": 0.16655084490776062,
      "learning_rate": 7.960937500000001e-05,
      "loss": 1.5827,
      "step": 2350
    },
    {
      "epoch": 0.625,
      "grad_norm": 0.22628355026245117,
      "learning_rate": 7.917534722222223e-05,
      "loss": 1.5864,
      "step": 2400
    },
    {
      "epoch": 0.6380208333333334,
      "grad_norm": 0.17180408537387848,
      "learning_rate": 7.874131944444445e-05,
      "loss": 1.6076,
      "step": 2450
    },
    {
      "epoch": 0.6510416666666666,
      "grad_norm": 0.21325701475143433,
      "learning_rate": 7.830729166666667e-05,
      "loss": 1.6211,
      "step": 2500
    },
    {
      "epoch": 0.6640625,
      "grad_norm": 0.17427074909210205,
      "learning_rate": 7.78732638888889e-05,
      "loss": 1.6062,
      "step": 2550
    },
    {
      "epoch": 0.6770833333333334,
      "grad_norm": 0.1645742803812027,
      "learning_rate": 7.743923611111112e-05,
      "loss": 1.6672,
      "step": 2600
    },
    {
      "epoch": 0.6901041666666666,
      "grad_norm": 0.16042818129062653,
      "learning_rate": 7.700520833333333e-05,
      "loss": 1.5636,
      "step": 2650
    },
    {
      "epoch": 0.703125,
      "grad_norm": 0.16018924117088318,
      "learning_rate": 7.657118055555556e-05,
      "loss": 1.5576,
      "step": 2700
    },
    {
      "epoch": 0.7161458333333334,
      "grad_norm": 0.17729054391384125,
      "learning_rate": 7.613715277777778e-05,
      "loss": 1.5723,
      "step": 2750
    },
    {
      "epoch": 0.7291666666666666,
      "grad_norm": 0.19298258423805237,
      "learning_rate": 7.5703125e-05,
      "loss": 1.59,
      "step": 2800
    },
    {
      "epoch": 0.7421875,
      "grad_norm": 0.21887212991714478,
      "learning_rate": 7.526909722222223e-05,
      "loss": 1.6676,
      "step": 2850
    },
    {
      "epoch": 0.7552083333333334,
      "grad_norm": 0.15565192699432373,
      "learning_rate": 7.483506944444446e-05,
      "loss": 1.5565,
      "step": 2900
    },
    {
      "epoch": 0.7682291666666666,
      "grad_norm": 0.15169097483158112,
      "learning_rate": 7.440104166666667e-05,
      "loss": 1.5872,
      "step": 2950
    },
    {
      "epoch": 0.78125,
      "grad_norm": 0.20027677714824677,
      "learning_rate": 7.396701388888889e-05,
      "loss": 1.6274,
      "step": 3000
    },
    {
      "epoch": 0.7942708333333334,
      "grad_norm": 0.1728917956352234,
      "learning_rate": 7.353298611111112e-05,
      "loss": 1.6312,
      "step": 3050
    },
    {
      "epoch": 0.8072916666666666,
      "grad_norm": 0.1673150658607483,
      "learning_rate": 7.309895833333333e-05,
      "loss": 1.6646,
      "step": 3100
    },
    {
      "epoch": 0.8203125,
      "grad_norm": 0.1909635215997696,
      "learning_rate": 7.266493055555555e-05,
      "loss": 1.6137,
      "step": 3150
    },
    {
      "epoch": 0.8333333333333334,
      "grad_norm": 0.196403369307518,
      "learning_rate": 7.223090277777778e-05,
      "loss": 1.6176,
      "step": 3200
    },
    {
      "epoch": 0.8463541666666666,
      "grad_norm": 0.19187861680984497,
      "learning_rate": 7.1796875e-05,
      "loss": 1.5964,
      "step": 3250
    },
    {
      "epoch": 0.859375,
      "grad_norm": 0.20234645903110504,
      "learning_rate": 7.136284722222223e-05,
      "loss": 1.5892,
      "step": 3300
    },
    {
      "epoch": 0.8723958333333334,
      "grad_norm": 0.23605573177337646,
      "learning_rate": 7.092881944444445e-05,
      "loss": 1.5237,
      "step": 3350
    },
    {
      "epoch": 0.8854166666666666,
      "grad_norm": 0.24045823514461517,
      "learning_rate": 7.049479166666668e-05,
      "loss": 1.6105,
      "step": 3400
    },
    {
      "epoch": 0.8984375,
      "grad_norm": 0.18747039139270782,
      "learning_rate": 7.006076388888889e-05,
      "loss": 1.6584,
      "step": 3450
    },
    {
      "epoch": 0.9114583333333334,
      "grad_norm": 0.16620966792106628,
      "learning_rate": 6.962673611111111e-05,
      "loss": 1.6372,
      "step": 3500
    },
    {
      "epoch": 0.9244791666666666,
      "grad_norm": 0.1983015090227127,
      "learning_rate": 6.919270833333334e-05,
      "loss": 1.581,
      "step": 3550
    },
    {
      "epoch": 0.9375,
      "grad_norm": 0.16401775181293488,
      "learning_rate": 6.875868055555555e-05,
      "loss": 1.5799,
      "step": 3600
    },
    {
      "epoch": 0.9505208333333334,
      "grad_norm": 0.1698988378047943,
      "learning_rate": 6.832465277777777e-05,
      "loss": 1.5808,
      "step": 3650
    },
    {
      "epoch": 0.9635416666666666,
      "grad_norm": 0.1724642962217331,
      "learning_rate": 6.789062500000001e-05,
      "loss": 1.5952,
      "step": 3700
    },
    {
      "epoch": 0.9765625,
      "grad_norm": 0.19811749458312988,
      "learning_rate": 6.745659722222222e-05,
      "loss": 1.5832,
      "step": 3750
    },
    {
      "epoch": 0.9895833333333334,
      "grad_norm": 0.13941513001918793,
      "learning_rate": 6.702256944444445e-05,
      "loss": 1.5722,
      "step": 3800
    },
    {
      "epoch": 1.0,
      "eval_loss": 1.5171061754226685,
      "eval_runtime": 66.4503,
      "eval_samples_per_second": 102.738,
      "eval_steps_per_second": 6.426,
      "step": 3840
    },
    {
      "epoch": 1.0026041666666667,
      "grad_norm": 0.18625473976135254,
      "learning_rate": 6.658854166666667e-05,
      "loss": 1.6078,
      "step": 3850
    },
    {
      "epoch": 1.015625,
      "grad_norm": 0.18472297489643097,
      "learning_rate": 6.61545138888889e-05,
      "loss": 1.6118,
      "step": 3900
    },
    {
      "epoch": 1.0286458333333333,
      "grad_norm": 0.2888626754283905,
      "learning_rate": 6.572048611111111e-05,
      "loss": 1.6472,
      "step": 3950
    },
    {
      "epoch": 1.0416666666666667,
      "grad_norm": 0.1957758367061615,
      "learning_rate": 6.528645833333333e-05,
      "loss": 1.616,
      "step": 4000
    },
    {
      "epoch": 1.0546875,
      "grad_norm": 0.1910765916109085,
      "learning_rate": 6.485243055555556e-05,
      "loss": 1.6381,
      "step": 4050
    },
    {
      "epoch": 1.0677083333333333,
      "grad_norm": 0.18344534933567047,
      "learning_rate": 6.441840277777777e-05,
      "loss": 1.6716,
      "step": 4100
    },
    {
      "epoch": 1.0807291666666667,
      "grad_norm": 0.1789036989212036,
      "learning_rate": 6.398437500000001e-05,
      "loss": 1.626,
      "step": 4150
    },
    {
      "epoch": 1.09375,
      "grad_norm": 0.17187699675559998,
      "learning_rate": 6.355034722222223e-05,
      "loss": 1.5948,
      "step": 4200
    },
    {
      "epoch": 1.1067708333333333,
      "grad_norm": 0.1547243297100067,
      "learning_rate": 6.311631944444444e-05,
      "loss": 1.6429,
      "step": 4250
    },
    {
      "epoch": 1.1197916666666667,
      "grad_norm": 0.18159595131874084,
      "learning_rate": 6.268229166666667e-05,
      "loss": 1.5925,
      "step": 4300
    },
    {
      "epoch": 1.1328125,
      "grad_norm": 0.19196464121341705,
      "learning_rate": 6.22482638888889e-05,
      "loss": 1.629,
      "step": 4350
    },
    {
      "epoch": 1.1458333333333333,
      "grad_norm": 0.18475548923015594,
      "learning_rate": 6.18142361111111e-05,
      "loss": 1.6038,
      "step": 4400
    },
    {
      "epoch": 1.1588541666666667,
      "grad_norm": 0.19323661923408508,
      "learning_rate": 6.138020833333333e-05,
      "loss": 1.5852,
      "step": 4450
    },
    {
      "epoch": 1.171875,
      "grad_norm": 0.25114259123802185,
      "learning_rate": 6.0946180555555555e-05,
      "loss": 1.6034,
      "step": 4500
    },
    {
      "epoch": 1.1848958333333333,
      "grad_norm": 0.18276609480381012,
      "learning_rate": 6.0512152777777773e-05,
      "loss": 1.5663,
      "step": 4550
    },
    {
      "epoch": 1.1979166666666667,
      "grad_norm": 0.1638273298740387,
      "learning_rate": 6.0078125000000005e-05,
      "loss": 1.5846,
      "step": 4600
    },
    {
      "epoch": 1.2109375,
      "grad_norm": 0.16677908599376678,
      "learning_rate": 5.964409722222223e-05,
      "loss": 1.5911,
      "step": 4650
    },
    {
      "epoch": 1.2239583333333333,
      "grad_norm": 0.250965416431427,
      "learning_rate": 5.921006944444445e-05,
      "loss": 1.6114,
      "step": 4700
    },
    {
      "epoch": 1.2369791666666667,
      "grad_norm": 0.1994151473045349,
      "learning_rate": 5.877604166666667e-05,
      "loss": 1.5833,
      "step": 4750
    },
    {
      "epoch": 1.25,
      "grad_norm": 0.2440577745437622,
      "learning_rate": 5.834201388888889e-05,
      "loss": 1.5744,
      "step": 4800
    },
    {
      "epoch": 1.2630208333333333,
      "grad_norm": 0.23329117894172668,
      "learning_rate": 5.790798611111111e-05,
      "loss": 1.6181,
      "step": 4850
    },
    {
      "epoch": 1.2760416666666667,
      "grad_norm": 0.16598953306674957,
      "learning_rate": 5.7473958333333334e-05,
      "loss": 1.6007,
      "step": 4900
    },
    {
      "epoch": 1.2890625,
      "grad_norm": 0.2574778199195862,
      "learning_rate": 5.703993055555555e-05,
      "loss": 1.5753,
      "step": 4950
    },
    {
      "epoch": 1.3020833333333333,
      "grad_norm": 0.16894319653511047,
      "learning_rate": 5.660590277777778e-05,
      "loss": 1.5955,
      "step": 5000
    },
    {
      "epoch": 1.3151041666666667,
      "grad_norm": 0.1991303414106369,
      "learning_rate": 5.617187500000001e-05,
      "loss": 1.6465,
      "step": 5050
    },
    {
      "epoch": 1.328125,
      "grad_norm": 0.19845186173915863,
      "learning_rate": 5.5737847222222226e-05,
      "loss": 1.588,
      "step": 5100
    },
    {
      "epoch": 1.3411458333333333,
      "grad_norm": 0.14441676437854767,
      "learning_rate": 5.530381944444445e-05,
      "loss": 1.6064,
      "step": 5150
    },
    {
      "epoch": 1.3541666666666667,
      "grad_norm": 0.18574339151382446,
      "learning_rate": 5.486979166666667e-05,
      "loss": 1.5907,
      "step": 5200
    },
    {
      "epoch": 1.3671875,
      "grad_norm": 0.19262224435806274,
      "learning_rate": 5.4435763888888894e-05,
      "loss": 1.5614,
      "step": 5250
    },
    {
      "epoch": 1.3802083333333333,
      "grad_norm": 0.18338064849376678,
      "learning_rate": 5.400173611111111e-05,
      "loss": 1.5899,
      "step": 5300
    },
    {
      "epoch": 1.3932291666666667,
      "grad_norm": 0.18007433414459229,
      "learning_rate": 5.356770833333333e-05,
      "loss": 1.6083,
      "step": 5350
    },
    {
      "epoch": 1.40625,
      "grad_norm": 0.18696025013923645,
      "learning_rate": 5.3133680555555555e-05,
      "loss": 1.6275,
      "step": 5400
    },
    {
      "epoch": 1.4192708333333333,
      "grad_norm": 0.27675193548202515,
      "learning_rate": 5.269965277777777e-05,
      "loss": 1.5551,
      "step": 5450
    },
    {
      "epoch": 1.4322916666666667,
      "grad_norm": 0.1823800951242447,
      "learning_rate": 5.2265625000000005e-05,
      "loss": 1.5996,
      "step": 5500
    },
    {
      "epoch": 1.4453125,
      "grad_norm": 0.1955018937587738,
      "learning_rate": 5.183159722222223e-05,
      "loss": 1.5656,
      "step": 5550
    },
    {
      "epoch": 1.4583333333333333,
      "grad_norm": 0.23429496586322784,
      "learning_rate": 5.139756944444445e-05,
      "loss": 1.5666,
      "step": 5600
    },
    {
      "epoch": 1.4713541666666667,
      "grad_norm": 0.2096157819032669,
      "learning_rate": 5.096354166666667e-05,
      "loss": 1.6191,
      "step": 5650
    },
    {
      "epoch": 1.484375,
      "grad_norm": 0.23123858869075775,
      "learning_rate": 5.052951388888889e-05,
      "loss": 1.5971,
      "step": 5700
    },
    {
      "epoch": 1.4973958333333333,
      "grad_norm": 0.220503568649292,
      "learning_rate": 5.009548611111111e-05,
      "loss": 1.6404,
      "step": 5750
    },
    {
      "epoch": 1.5104166666666665,
      "grad_norm": 0.19406066834926605,
      "learning_rate": 4.966145833333334e-05,
      "loss": 1.5721,
      "step": 5800
    },
    {
      "epoch": 1.5234375,
      "grad_norm": 0.19639591872692108,
      "learning_rate": 4.922743055555556e-05,
      "loss": 1.6212,
      "step": 5850
    },
    {
      "epoch": 1.5364583333333335,
      "grad_norm": 0.17913734912872314,
      "learning_rate": 4.8793402777777783e-05,
      "loss": 1.5937,
      "step": 5900
    },
    {
      "epoch": 1.5494791666666665,
      "grad_norm": 0.21192431449890137,
      "learning_rate": 4.8359375e-05,
      "loss": 1.6089,
      "step": 5950
    },
    {
      "epoch": 1.5625,
      "grad_norm": 0.19240829348564148,
      "learning_rate": 4.792534722222222e-05,
      "loss": 1.5322,
      "step": 6000
    },
    {
      "epoch": 1.5755208333333335,
      "grad_norm": 0.23641838133335114,
      "learning_rate": 4.749131944444445e-05,
      "loss": 1.5998,
      "step": 6050
    },
    {
      "epoch": 1.5885416666666665,
      "grad_norm": 0.19334276020526886,
      "learning_rate": 4.705729166666667e-05,
      "loss": 1.6152,
      "step": 6100
    },
    {
      "epoch": 1.6015625,
      "grad_norm": 0.2036045491695404,
      "learning_rate": 4.662326388888889e-05,
      "loss": 1.601,
      "step": 6150
    },
    {
      "epoch": 1.6145833333333335,
      "grad_norm": 0.18101830780506134,
      "learning_rate": 4.618923611111111e-05,
      "loss": 1.5669,
      "step": 6200
    },
    {
      "epoch": 1.6276041666666665,
      "grad_norm": 0.21720461547374725,
      "learning_rate": 4.575520833333334e-05,
      "loss": 1.613,
      "step": 6250
    },
    {
      "epoch": 1.640625,
      "grad_norm": 0.16520608961582184,
      "learning_rate": 4.532118055555556e-05,
      "loss": 1.5658,
      "step": 6300
    },
    {
      "epoch": 1.6536458333333335,
      "grad_norm": 0.20340947806835175,
      "learning_rate": 4.488715277777778e-05,
      "loss": 1.5587,
      "step": 6350
    },
    {
      "epoch": 1.6666666666666665,
      "grad_norm": 0.21329611539840698,
      "learning_rate": 4.4453125e-05,
      "loss": 1.6027,
      "step": 6400
    },
    {
      "epoch": 1.6796875,
      "grad_norm": 0.16999514400959015,
      "learning_rate": 4.401909722222222e-05,
      "loss": 1.5466,
      "step": 6450
    },
    {
      "epoch": 1.6927083333333335,
      "grad_norm": 0.21583253145217896,
      "learning_rate": 4.358506944444445e-05,
      "loss": 1.6037,
      "step": 6500
    },
    {
      "epoch": 1.7057291666666665,
      "grad_norm": 0.14665327966213226,
      "learning_rate": 4.315104166666667e-05,
      "loss": 1.5642,
      "step": 6550
    },
    {
      "epoch": 1.71875,
      "grad_norm": 0.20301412045955658,
      "learning_rate": 4.271701388888889e-05,
      "loss": 1.5868,
      "step": 6600
    },
    {
      "epoch": 1.7317708333333335,
      "grad_norm": 0.19513314962387085,
      "learning_rate": 4.228298611111111e-05,
      "loss": 1.5955,
      "step": 6650
    },
    {
      "epoch": 1.7447916666666665,
      "grad_norm": 0.20196516811847687,
      "learning_rate": 4.184895833333334e-05,
      "loss": 1.6327,
      "step": 6700
    },
    {
      "epoch": 1.7578125,
      "grad_norm": 0.20568954944610596,
      "learning_rate": 4.141493055555556e-05,
      "loss": 1.6311,
      "step": 6750
    },
    {
      "epoch": 1.7708333333333335,
      "grad_norm": 0.21317347884178162,
      "learning_rate": 4.098090277777778e-05,
      "loss": 1.5978,
      "step": 6800
    },
    {
      "epoch": 1.7838541666666665,
      "grad_norm": 0.23402048647403717,
      "learning_rate": 4.0546875e-05,
      "loss": 1.597,
      "step": 6850
    },
    {
      "epoch": 1.796875,
      "grad_norm": 0.2168450951576233,
      "learning_rate": 4.011284722222222e-05,
      "loss": 1.5903,
      "step": 6900
    },
    {
      "epoch": 1.8098958333333335,
      "grad_norm": 0.1955851912498474,
      "learning_rate": 3.967881944444445e-05,
      "loss": 1.5861,
      "step": 6950
    },
    {
      "epoch": 1.8229166666666665,
      "grad_norm": 0.18039576709270477,
      "learning_rate": 3.924479166666667e-05,
      "loss": 1.6224,
      "step": 7000
    },
    {
      "epoch": 1.8359375,
      "grad_norm": 0.21834686398506165,
      "learning_rate": 3.881076388888889e-05,
      "loss": 1.5887,
      "step": 7050
    },
    {
      "epoch": 1.8489583333333335,
      "grad_norm": 0.21235650777816772,
      "learning_rate": 3.837673611111111e-05,
      "loss": 1.6189,
      "step": 7100
    },
    {
      "epoch": 1.8619791666666665,
      "grad_norm": 0.23602432012557983,
      "learning_rate": 3.794270833333334e-05,
      "loss": 1.5935,
      "step": 7150
    },
    {
      "epoch": 1.875,
      "grad_norm": 0.2125622034072876,
      "learning_rate": 3.750868055555556e-05,
      "loss": 1.5814,
      "step": 7200
    },
    {
      "epoch": 1.8880208333333335,
      "grad_norm": 0.19668224453926086,
      "learning_rate": 3.707465277777778e-05,
      "loss": 1.5939,
      "step": 7250
    },
    {
      "epoch": 1.9010416666666665,
      "grad_norm": 0.211033895611763,
      "learning_rate": 3.6640625e-05,
      "loss": 1.5875,
      "step": 7300
    },
    {
      "epoch": 1.9140625,
      "grad_norm": 0.22179928421974182,
      "learning_rate": 3.620659722222222e-05,
      "loss": 1.6018,
      "step": 7350
    },
    {
      "epoch": 1.9270833333333335,
      "grad_norm": 0.21585677564144135,
      "learning_rate": 3.577256944444445e-05,
      "loss": 1.582,
      "step": 7400
    },
    {
      "epoch": 1.9401041666666665,
      "grad_norm": 0.18672429025173187,
      "learning_rate": 3.533854166666667e-05,
      "loss": 1.5908,
      "step": 7450
    },
    {
      "epoch": 1.953125,
      "grad_norm": 0.23389071226119995,
      "learning_rate": 3.490451388888889e-05,
      "loss": 1.591,
      "step": 7500
    },
    {
      "epoch": 1.9661458333333335,
      "grad_norm": 0.17544110119342804,
      "learning_rate": 3.447048611111111e-05,
      "loss": 1.6231,
      "step": 7550
    },
    {
      "epoch": 1.9791666666666665,
      "grad_norm": 0.20883995294570923,
      "learning_rate": 3.403645833333334e-05,
      "loss": 1.6125,
      "step": 7600
    },
    {
      "epoch": 1.9921875,
      "grad_norm": 0.19980807602405548,
      "learning_rate": 3.360243055555556e-05,
      "loss": 1.5562,
      "step": 7650
    },
    {
      "epoch": 2.0,
      "eval_loss": 1.5091774463653564,
      "eval_runtime": 63.3168,
      "eval_samples_per_second": 107.823,
      "eval_steps_per_second": 6.744,
      "step": 7680
    }
  ],
  "logging_steps": 50,
  "max_steps": 11520,
  "num_input_tokens_seen": 0,
  "num_train_epochs": 3,
  "save_steps": 500,
  "stateful_callbacks": {
    "TrainerControl": {
      "args": {
        "should_epoch_stop": false,
        "should_evaluate": false,
        "should_log": false,
        "should_save": true,
        "should_training_stop": false
      },
      "attributes": {}
    }
  },
  "total_flos": 6167451999141888.0,
  "train_batch_size": 16,
  "trial_name": null,
  "trial_params": null
}
